odoo/addons/purchase_billing_address/README.rst
odoo/addons/purchase_billing_address/__init__.py
odoo/addons/purchase_billing_address/__manifest__.py
odoo/addons/purchase_billing_address/i18n/it.po
odoo/addons/purchase_billing_address/i18n/purchase_billing_address.pot
odoo/addons/purchase_billing_address/models/__init__.py
odoo/addons/purchase_billing_address/models/purchase_order.py
odoo/addons/purchase_billing_address/models/res_partner.py
odoo/addons/purchase_billing_address/readme/CONTRIBUTORS.md
odoo/addons/purchase_billing_address/readme/DESCRIPTION.md
odoo/addons/purchase_billing_address/readme/USAGE.md
odoo/addons/purchase_billing_address/static/description/icon.png
odoo/addons/purchase_billing_address/static/description/index.html
odoo/addons/purchase_billing_address/static/img/readme/ADDRESS_PURCHASE.png
odoo/addons/purchase_billing_address/static/img/readme/PURCHASE_INVOICE.png
odoo/addons/purchase_billing_address/static/img/readme/SELECT_ADDRESS_PURCHASE.png
odoo/addons/purchase_billing_address/tests/__init__.py
odoo/addons/purchase_billing_address/tests/test_purchase_invoice_partner_type.py
odoo/addons/purchase_billing_address/views/purchase_order_views.xml
odoo_addon_purchase_billing_address-17.0.1.0.0.3.dist-info/METADATA
odoo_addon_purchase_billing_address-17.0.1.0.0.3.dist-info/WHEEL
odoo_addon_purchase_billing_address-17.0.1.0.0.3.dist-info/top_level.txt
odoo_addon_purchase_billing_address-17.0.1.0.0.3.dist-info/RECORD
