Metadata-Version: 2.1
Name: odoo-addon-purchase_billing_address
Version: 17.0.1.0.0.3
Requires-Python: >=3.10
Requires-Dist: odoo>=17.0a,<17.1dev
Summary: Create a new partner type (purchase), to differentiate the purchase order and invoice addresses.
Home-page: https://github.com/OCA/purchase-workflow
License: AGPL-3
Author: Binhex <https://www.binhex.cloud>,Odoo Community Association (OCA)
Author-email: support@odoo-community.org
Classifier: Programming Language :: Python
Classifier: Framework :: Odoo
Classifier: Framework :: Odoo :: 17.0
Classifier: License :: OSI Approved :: GNU Affero General Public License v3
